MANIFEST.in
README.rst
setup.py
aliyun_python_sdk_cusanalytic_sc_online.egg-info/PKG-INFO
aliyun_python_sdk_cusanalytic_sc_online.egg-info/SOURCES.txt
aliyun_python_sdk_cusanalytic_sc_online.egg-info/dependency_links.txt
aliyun_python_sdk_cusanalytic_sc_online.egg-info/requires.txt
aliyun_python_sdk_cusanalytic_sc_online.egg-info/top_level.txt
aliyunsdkcusanalytic_sc_online/__init__.py
aliyunsdkcusanalytic_sc_online/endpoint.py
aliyunsdkcusanalytic_sc_online/request/__init__.py
aliyunsdkcusanalytic_sc_online/request/v20190524/DescribeActionDataRequest.py
aliyunsdkcusanalytic_sc_online/request/v20190524/DescribeLocationsRequest.py
aliyunsdkcusanalytic_sc_online/request/v20190524/GetActionCursorRequest.py
aliyunsdkcusanalytic_sc_online/request/v20190524/GetAnalyzeCommodityDataRequest.py
aliyunsdkcusanalytic_sc_online/request/v20190524/GetAnalyzePlaceDataRequest.py
aliyunsdkcusanalytic_sc_online/request/v20190524/GetEMapRequest.py
aliyunsdkcusanalytic_sc_online/request/v20190524/GetHeatMapDataRequest.py
aliyunsdkcusanalytic_sc_online/request/v20190524/GetImageUrlRequest.py
aliyunsdkcusanalytic_sc_online/request/v20190524/GetLocationsRequest.py
aliyunsdkcusanalytic_sc_online/request/v20190524/GetOverviewDataRequest.py
aliyunsdkcusanalytic_sc_online/request/v20190524/GetPortrayalRequest.py
aliyunsdkcusanalytic_sc_online/request/v20190524/GetSupportStoreRequest.py
aliyunsdkcusanalytic_sc_online/request/v20190524/ListVisitorsRequest.py
aliyunsdkcusanalytic_sc_online/request/v20190524/SearchPersonByImgRequest.py
aliyunsdkcusanalytic_sc_online/request/v20190524/__init__.py